gtd/LICENSE
gtd/README.md
gtd/pyproject.toml
gtd/dist/gtd-0.1.0-py3-none-any.whl
gtd/dist/gtd-0.1.0.tar.gz
gtd/gtd/__init__.py
gtd/gtd/gtd.py
gtd_cli_tool-0.1.0.dist-info/METADATA
gtd_cli_tool-0.1.0.dist-info/WHEEL
gtd_cli_tool-0.1.0.dist-info/entry_points.txt
gtd_cli_tool-0.1.0.dist-info/RECORD
