Metadata-Version: 2.4
Name: gtd-cli-tool
Version: 0.1.0
Summary: A YouTube video downloader CLI tool
Project-URL: Homepage, https://github.com/yourusername/gtd
Project-URL: Repository, https://github.com/yourusername/gtd.git
Project-URL: Issues, https://github.com/yourusername/gtd/issues
Author-email: Your Name <your.email@example.com>
License-Expression: MIT
Requires-Python: >=3.7
Requires-Dist: rich>=13.0.0
Requires-Dist: typer>=0.9.0
Requires-Dist: yt-dlp>=2023.0.0
